generator.py
main.py
scanner.py
castorscribe-1.0.0.dist-info/METADATA
castorscribe-1.0.0.dist-info/WHEEL
castorscribe-1.0.0.dist-info/entry_points.txt
castorscribe-1.0.0.dist-info/top_level.txt
castorscribe-1.0.0.dist-info/RECORD
