Metadata-Version: 2.4
Name: castorscribe
Version: 1.0.0
Summary: Automated README.md generator powered by AI - analyzes your project and creates professional documentation
Author-email: Aadiy Khan <aadiykhan@gmail.com>
License: MIT
Project-URL: Homepage, https://github.com/AadiyKhan/readme-generator
Keywords: readme,generator,documentation,ai,automation,markdown
Classifier: Development Status :: 4 - Beta
Classifier: Intended Audience :: Developers
Classifier: Topic :: Software Development :: Documentation
Classifier: Programming Language :: Python :: 3
Classifier: Operating System :: OS Independent
Requires-Python: >=3.8
Requires-Dist: google-genai>=1.0.0
